{
  "css_path": "c:\\Users\\朱羿安\\Desktop\\北商二技\\二技專題\\0706_flask_(byMike加入社群討論區)\\0706_flask_\\static\\css\\modules\\social\\social_main.css",
  "total_classes": 166,
  "used_count": 161,
  "unused_count": 5,
  "used": [
    "2s",
    "3s",
    "5s",
    "6s",
    "8s",
    "action-btn",
    "active",
    "announcement-board",
    "announcement-body",
    "announcement-scroller",
    "anonymous-badge",
    "anonymous-icon",
    "author-actions",
    "author-badge",
    "back-btn",
    "btn",
    "btn-danger",
    "btn-emoji",
    "btn-follow",
    "btn-info",
    "btn-primary",
    "btn-remove",
    "btn-secondary",
    "btn-sm",
    "btn-unfollow",
    "btn-warning",
    "cancel-reply",
    "char-count",
    "char-counter",
    "checkbox-label",
    "close-btn",
    "close-comments",
    "close-modal-btn",
    "comment-actions",
    "comment-author",
    "comment-btn",
    "comment-char-count",
    "comment-content",
    "comment-form",
    "comment-header",
    "comment-input-group",
    "comment-item",
    "comment-time",
    "comments-header",
    "comments-list",
    "comments-section",
    "content-flex",
    "current-progress",
    "custom-header",
    "danger",
    "dark-mode",
    "delete-comment-btn",
    "delete-post-btn",
    "edit-comment-btn",
    "edit-comment-modal",
    "edit-comment-modal-body",
    "edit-comment-modal-footer",
    "edit-comment-modal-header",
    "edit-comment-modal-overlay",
    "edit-modal",
    "edit-modal-body",
    "edit-modal-footer",
    "edit-modal-header",
    "edit-modal-overlay",
    "edit-post-btn",
    "emoji-fallback",
    "empty-follow-list",
    "empty-icon",
    "feature-modal-box",
    "feature-modal-overlay",
    "follow-btn",
    "follow-modal",
    "follow-modal-body",
    "follow-modal-header",
    "follow-modal-overlay",
    "follow-notification",
    "follow-user-actions",
    "follow-user-avatar",
    "follow-user-details",
    "follow-user-info",
    "follow-user-item",
    "follow-user-level",
    "following",
    "following-actions",
    "footer",
    "form-control",
    "form-group",
    "info",
    "level-actions",
    "level-description",
    "level-emoji",
    "level-header",
    "level-icon",
    "level-info",
    "level-points",
    "level-progress",
    "level-stats",
    "level-up-close",
    "level-up-content",
    "level-up-icon",
    "level-up-notification",
    "level-up-text",
    "like-btn",
    "modal-overlay",
    "mood-emoji",
    "mood-indicator",
    "mood-tag",
    "mood-tags",
    "more-item",
    "more-menu",
    "more-wrapper",
    "next-level",
    "no-comments",
    "no-filtered-posts",
    "no-posts",
    "no-posts-icon",
    "notification-close",
    "notification-content",
    "page-wrapper",
    "points-label",
    "points-value",
    "post-card",
    "post-image",
    "post-list",
    "post-title",
    "progress-bar",
    "progress-fill",
    "progress-text",
    "reply-comment-btn",
    "reply-indicator",
    "reply-info",
    "reply-prefix",
    "reply-target",
    "reply-text",
    "report-btn",
    "repost-btn",
    "scroll-area",
    "search-bar",
    "search-btn",
    "search-input",
    "selected",
    "share-btn",
    "social-nav",
    "social-stat-icon",
    "social-stat-item",
    "social-stat-label",
    "social-stat-number",
    "social-stat-value",
    "social-stats",
    "stat-icon",
    "stat-item",
    "stat-label",
    "stat-value",
    "submit-comment-btn",
    "tag",
    "tag-panel",
    "updated",
    "user-card",
    "user-level-card",
    "user-name",
    "warning"
  ],
  "unused": [
    "dark_mode",
    "edit-modal_body",
    "follow-actions",
    "unfollow-btn",
    "updating"
  ]
}